openapi_readme/__init__.py
openapi_readme/main.py
openapi_readme-0.4.0.dist-info/METADATA
openapi_readme-0.4.0.dist-info/WHEEL
openapi_readme-0.4.0.dist-info/entry_points.txt
openapi_readme-0.4.0.dist-info/licenses/LICENSE.txt
openapi_readme-0.4.0.dist-info/RECORD
