Metadata-Version: 2.3
Name: openapi-readme
Version: 0.4.0
Summary: Generate Markdown from an openapi JSON file.
Project-URL: repository, https://github.com/seapagan/openapi-readme
Project-URL: homepage, https://github.com/seapagan/openapi-readme
Project-URL: Pull Requests, https://github.com/seapagan/openapi-readme/pulls
Project-URL: Bug Tracker, https://github.com/seapagan/openapi-readme/issues
Project-URL: Changelog, https://github.com/seapagan/openapi-readme/blob/main/CHANGELOG.md
Author-email: Grant Ramsay <grant@gnramsay.com>
License-Expression: MIT
License-File: LICENSE.txt
Classifier: Development Status :: 4 - Beta
Classifier: Environment :: Console
Classifier: Intended Audience :: Developers
Classifier: Operating System :: OS Independent
Classifier: Programming Language :: Python :: 3
Classifier: Programming Language :: Python :: 3.9
Classifier: Programming Language :: Python :: 3.10
Classifier: Programming Language :: Python :: 3.11
Classifier: Programming Language :: Python :: 3.12
Classifier: Topic :: Text Processing :: Markup :: Markdown
Requires-Python: >=3.9
Requires-Dist: single-source>=0.4.0
Requires-Dist: typer>=0.12.5
